MANIFEST.in
VERSION.txt
setup.py
yolodb/__init__.py
yolodb/yolodb.py
yolodb.egg-info/PKG-INFO
yolodb.egg-info/SOURCES.txt
yolodb.egg-info/dependency_links.txt
yolodb.egg-info/top_level.txt