Metadata-Version: 1.1
Name: yolodb
Version: 0.3.0
Summary: A simple key/value storage DB (well... json)
Home-page: https://github.com/gdraynz/yolodb
Author: gdraynz
Author-email: gd.raynz@gmail.com
License: WTFPL
Platform: UNKNOWN
Classifier: Development Status :: 4 - Beta
Classifier: Intended Audience :: Developers
Classifier: Natural Language :: English
Classifier: Programming Language :: Python :: 3 :: Only
Classifier: Programming Language :: Python :: 3.5
